tictactoe_gym/__init__.py
tictactoe_gym/envs/__init__.py
tictactoe_gym/envs/tictactoe_env.py
tictactoe_gym/example/play_game.py
tictactoe_gym-1.0.1.dist-info/LICENSE.md
tictactoe_gym-1.0.1.dist-info/METADATA
tictactoe_gym-1.0.1.dist-info/WHEEL
tictactoe_gym-1.0.1.dist-info/top_level.txt
tictactoe_gym-1.0.1.dist-info/RECORD
