Metadata-Version: 2.1
Name: tictactoe-gym
Version: 1.0.1
Summary: An OpenAI gym environment for playing Tic Tac Toe
Home-page: https://github.com/alfiebeard/tictactoe-gym
Author: Alfie Beard
License: MIT License        
Project-URL: Homepage, https://github.com/alfiebeard/tictactoe-gym
Keywords: tictactoe,gym
Classifier: License :: OSI Approved :: MIT License
Classifier: Programming Language :: Python
Classifier: Programming Language :: Python :: 3
Requires-Python: >=3.10
License-File: LICENSE.md
Requires-Dist: gym
